bibt/gcp/scc/__init__.py
bibt/gcp/scc/classes.py
bibt/gcp/scc/methods.py
bibt/gcp/scc/version.py
bibt_gcp_scc-1.1.11.dist-info/METADATA
bibt_gcp_scc-1.1.11.dist-info/WHEEL
bibt_gcp_scc-1.1.11.dist-info/licenses/LICENSE
bibt_gcp_scc-1.1.11.dist-info/RECORD
