Metadata-Version: 2.3
Name: bibt-gcp-scc
Version: 1.1.11
Summary: Functionality often used by BITS Blue Team (GCP SCC Module).
Project-URL: Bug Tracker, https://github.com/broadinstitute/bibt-gcp-scc/issues
Project-URL: Documentation, https://bibt-gcp-scc.readthedocs.io/en/latest/
Project-URL: Homepage, https://github.com/broadinstitute/bibt-gcp-scc
Author-email: Matthew OBrien <mobrien@broadinstitute.org>
Classifier: License :: OSI Approved :: MIT License
Classifier: Operating System :: OS Independent
Classifier: Programming Language :: Python :: 3
Classifier: Programming Language :: Python :: 3.9
Classifier: Programming Language :: Python :: 3.10
Classifier: Programming Language :: Python :: 3.11
Classifier: Programming Language :: Python :: 3.12
Classifier: Topic :: Security
Classifier: Topic :: Software Development :: Libraries
Classifier: Topic :: Utilities
Requires-Python: >=3.7
Requires-Dist: google-cloud-securitycenter==1.25.0
Requires-Dist: googleapis-common-protos==1.62.0
Requires-Dist: inflection==0.5.1
Requires-Dist: protobuf==4.25.1
Requires-Dist: pytz==2023.3
